<?xml version="1.0" encoding="UTF-8" standalone="yes"?>
<program xmlns="urn:vpro:media:2009" xmlns:shared="urn:vpro:shared:2009" type="BROADCAST" avType="VIDEO" embeddable="true" mid="RCRST1_0719908022923" sortDate="2026-04-01T18:00:00+02:00" workflow="FOR PUBLICATION" creationDate="2026-02-11T01:04:28.290+01:00">
    <broadcaster id="AVTR">AVTR</broadcaster>
    <title owner="AUTHORITY" type="MAIN">EenVandaag</title>
    <description owner="AUTHORITY" type="MAIN">Het actualiteitenprogramma EenVandaag wordt dagelijks uitgezonden tussen 16.00 uur en 17.00 uur op NPO Radio 1. De presentatie is in handen van Suzanne Bosman.</description>
    <genre id="3.0.1.7.21">
        <term>Informatief</term>
        <term>Nieuws/actualiteiten</term>
    </genre>
    <credits/>
    <ageRating>ALL</ageRating>
    <locations/>
    <images/>
    <scheduleEvents>
        <scheduleEvent channel="RAD1" midRef="RCRST1_0719908022923">
            <guideDay>2026-04-01+02:00</guideDay>
            <start>2026-04-01T18:00:00+02:00</start>
            <duration>P68Y0M18DT3H14M7.000S</duration>
            <poProgID>RCRST1_0719908022923</poProgID>
        </scheduleEvent>
    </scheduleEvents>
    <segments/>
</program>
