<?xml version="1.0" encoding="UTF-8" standalone="yes"?>
<program xmlns="urn:vpro:media:2009" xmlns:shared="urn:vpro:shared:2009" type="BROADCAST" avType="VIDEO" embeddable="true" mid="POW_00288337" sortDate="2013-02-05T13:28:33.458+01:00" workflow="FOR PUBLICATION" creationDate="2013-02-05T13:28:33.456+01:00">
    <crid>crid://metadatahub.bijnpo.nl/66c87c74-bfe8-4e79-8e10-89a3d273678a</crid>
    <crid>crid://tmp.program.omroep.nl/10576785</crid>
    <broadcaster id="MAX">MAX</broadcaster>
    <title owner="AUTHORITY" type="MAIN">Nederland in Beweging!</title>
    <description owner="AUTHORITY" type="MAIN">Ouderen slapen meestal korter en minder diep. Dit hoort bij de leeftijd. Het is normaal om af en toe even wakker te worden, met name tegen de ochtend als de slaap minder diep is. Van slapeloosheid is pas sprake als je vaker slecht slaapt en overdag door te weinig nachtrust minder goed functioneert. Presentatie: Olga Commandeur, Duco Bauwens.</description>
    <genre id="3.0.1.4">
        <term>Sport</term>
    </genre>
    <credits>
        <person role="PRESENTER">
            <givenName></givenName>
            <familyName>Olga Commandeur</familyName>
        </person>
    </credits>
    <descendantOf midRef="http://metadatahub.bijnpo.nl/d134479e-4ff9-410b-9394-ae8dc107d304,16"/>
    <locations/>
    <images/>
    <scheduleEvents>
        <scheduleEvent channel="NED1" midRef="POW_00288337">
            <guideDay>2010-01-26+01:00</guideDay>
            <start>2010-01-26T06:45:00+01:00</start>
            <duration>P26Y7M13DT5H20M0.000S</duration>
            <poProgID>POW_00288337</poProgID>
        </scheduleEvent>
        <scheduleEvent channel="NED1" midRef="POW_00288337">
            <guideDay>2010-01-26+01:00</guideDay>
            <start>2010-01-26T09:15:00+01:00</start>
            <duration>P28Y6M8DT16H0M0.000S</duration>
            <poProgID>POW_00288337</poProgID>
        </scheduleEvent>
        <scheduleEvent channel="NVOD" midRef="POW_00288337">
            <guideDay>2013-02-05+01:00</guideDay>
            <start>2013-02-05T13:28:33.458+01:00</start>
            <poProgID>POW_00288337</poProgID>
        </scheduleEvent>
    </scheduleEvents>
    <episodeOf highlighted="false" midRef="http://metadatahub.bijnpo.nl/d134479e-4ff9-410b-9394-ae8dc107d304,16" index="1"/>
    <segments/>
</program>
