{ "head": {
    "vars": [ "entity" , "title" , "description" , "alternativeDescriptions" , "dateCreated" , "ebuFormat" , "crids" , "scheduleEvents" , "broadcasters" , "countries" , "genres" , "targetGroups" , "ageRating" , "contentRatings" , "persons" , "episodeOfSeasons" ]
  } ,
  "results": {
    "bindings": [
      { 
        "entity": { "type": "uri" , "value": "http://metadatahub.bijnpo.nl/df4a6647-1e87-4673-a69d-d175a4a9bde8" } ,
        "title": { "type": "literal" , "value": "ONM" } ,
        "alternativeDescriptions": { "type": "literal" , "value": "" } ,
        "dateCreated": { "type": "literal" , "datatype": "http://www.w3.org/2001/XMLSchema#dateTime" , "value": "2013-02-16T19:57:50.211Z" } ,
        "ebuFormat": { "type": "uri" , "value": "http://www.ebu.ch/metadata/ontologies/ebucoreplus#VideoFormat" } ,
        "crids": { "type": "literal" , "value": "crid://tmp.program.omroep.nl/10567676" } ,
        "scheduleEvents": { "type": "literal" , "value": "NPO 1,2010-01-26T14:35:00.000Z,1500000.0|NPO 3 & Zapp,2010-01-31T00:25:00.000Z,1200000.0|NPO 3 & Zapp,2010-01-25T18:00:00.000Z,1320000.0|INTERNETVOD,2013-02-16T19:57:50.213Z,|INTERNETVOD,2013-02-16T19:57:50.214Z," } ,
        "broadcasters": { "type": "literal" , "value": "BNN" } ,
        "countries": { "type": "literal" , "value": "" } ,
        "genres": { "type": "literal" , "value": "3.0.1.3" } ,
        "targetGroups": { "type": "literal" , "value": "" } ,
        "ageRating": { "type": "literal" , "value": "9" } ,
        "contentRatings": { "type": "literal" , "value": "" } ,
        "episodeOfSeasons": { "type": "literal" , "value": "http://metadatahub.bijnpo.nl/159230cf-5baa-4bef-a6ce-83f9872657fe,16" }
      }
    ]
  }
}
{ "head": {
    "vars": [ "prid" , "title" , "description" , "dateCreated" , "broadcasters" ]
  } ,
  "results": {
    "bindings": [
      
    ]
  }
}
