<?xml version="1.0" encoding="UTF-8" standalone="yes"?>
<program xmlns="urn:vpro:media:2009" xmlns:shared="urn:vpro:shared:2009" type="BROADCAST" avType="VIDEO" embeddable="true" mid="POW_00260673" sortDate="2013-02-15T21:50:41.309+01:00" workflow="FOR PUBLICATION" creationDate="2013-02-15T21:50:41.307+01:00">
    <crid>crid://tmp.program.omroep.nl/10576805</crid>
    <broadcaster id="NOS">NOS</broadcaster>
    <title owner="AUTHORITY" type="MAIN">NOS Journaal</title>
    <genre id="3.0.1.7.21">
        <term>Informatief</term>
        <term>Nieuws/actualiteiten</term>
    </genre>
    <credits/>
    <locations/>
    <images/>
    <scheduleEvents>
        <scheduleEvent channel="NED1" midRef="POW_00260673">
            <guideDay>2010-01-26+01:00</guideDay>
            <start>2010-01-26T18:00:00+01:00</start>
            <duration>P28Y6M8DT16H0M0.000S</duration>
            <poProgID>POW_00260673</poProgID>
        </scheduleEvent>
        <scheduleEvent channel="NVOD" midRef="POW_00260673">
            <guideDay>2013-02-15+01:00</guideDay>
            <start>2013-02-15T21:50:41.309+01:00</start>
            <poProgID>POW_00260673</poProgID>
        </scheduleEvent>
    </scheduleEvents>
    <segments/>
</program>
