<?xml version="1.0" encoding="UTF-8" standalone="yes"?>
<program xmlns="urn:vpro:media:2009" xmlns:shared="urn:vpro:shared:2009" type="BROADCAST" avType="VIDEO" embeddable="true" mid="POW_06008153" sortDate="2026-03-01T09:25:00+01:00" workflow="FOR PUBLICATION" creationDate="2026-02-28T17:20:21.869+01:00">
    <title owner="BROADCASTER" type="MAIN">NOS Journaal ivm aanval Israël/VS op Iran</title>
    <description owner="BROADCASTER" type="MAIN">Met het laatste nieuws en de weersverwachting.</description>
    <genre id="3.0.1.7.21">
        <term>Informatief</term>
        <term>Nieuws/actualiteiten</term>
    </genre>
    <credits/>
    <ageRating>ALL</ageRating>
    <locations/>
    <images/>
    <scheduleEvents>
        <scheduleEvent channel="NED1" midRef="POW_06008153">
            <guideDay>2026-03-01+01:00</guideDay>
            <start>2026-03-01T09:00:00+01:00</start>
            <duration>P0DT0H0M0.000S</duration>
            <poProgID>POW_06008153</poProgID>
        </scheduleEvent>
        <scheduleEvent channel="NED1" midRef="POW_06008153">
            <guideDay>2026-03-01+01:00</guideDay>
            <start>2026-03-01T09:25:00+01:00</start>
            <duration>P0DT0H0M0.000S</duration>
            <poProgID>POW_06008153</poProgID>
        </scheduleEvent>
    </scheduleEvents>
    <segments/>
</program>
