{
  "success" : true,
  "statusCode" : 200,
  "data" : {
    "@context" : "https://ontology.metadatahub.bijnpo.nl/context.json",
    "@id" : "http://metadatahub.bijnpo.nl/fa77fc39-01bf-496f-ba72-cc3dedf8f2a8",
    "@type" : "Programme",
    "hasAlternativeContentDescription" : [ {
      "@id" : "http://metadatahub.bijnpo.nl/0156f844-864e-421f-9be3-d7a7b7286481",
      "@type" : "AlternativeContentDescription",
      "contentDescription" : "Sandra maakt toast met tuinbonenspread en een gepocheerd ei met frisse citroenyoghurt. Een echt lentegerecht.",
      "hasObjectType" : {
        "@id" : "http://metadatahub.bijnpo.nl/afc0a6bd-9554-4de3-8ae9-5e7db77432fd",
        "@type" : [ "Concept", "NamedIndividual" ],
        "definition" : "The short description of the work.",
        "inScheme" : {
          "@id" : "npo_o:alternativeContentDescriptionTypes"
        },
        "prefLabel" : "Short description"
      }
    } ],
    "hasProductionCountry" : [ {
      "@id" : "http://metadatahub.bijnpo.nl/747889dd-cd33-4ef8-bd0b-424bc4df7532",
      "@type" : "CountryCode",
      "altLabel" : "NL",
      "prefLabel" : "Nederland"
    } ],
    "contentDescription" : "Sandra maakt toast met tuinbonenspread en een gepocheerd ei met frisse citroenyoghurt. Een echt lentegerecht.",
    "episodeNumberInSeason" : {
      "@type" : "integer",
      "@value" : "47"
    },
    "hasContributor" : [ {
      "@id" : "http://metadatahub.bijnpo.nl/dfd03035-b3d9-450b-99ca-1b3f3981f978",
      "@type" : "Involvement",
      "hasAgent" : {
        "@id" : "http://metadatahub.bijnpo.nl/25cd5803-7396-4076-aa6e-a8b95de759ca",
        "@type" : "Person",
        "familyName" : "Ysbrandy",
        "givenName" : "Sandra"
      },
      "hasObjectType" : {
        "@id" : "http://metadatahub.bijnpo.nl/f2627a7f-9503-430e-8bb4-110ad67f5c14",
        "@type" : "Concept",
        "date" : "2007-04-12",
        "definition" : "A person who introduces or hosts a programme, acting as the central moderator responsible for guiding the programme toward the audience.",
        "inScheme" : {
          "@id" : "urn:ebu:metadata-cs:RoleCodeCS"
        },
        "notation" : "25.10",
        "prefLabel" : "Presenter"
      }
    } ],
    "hasDateCreated" : {
      "@type" : "dateTime",
      "@value" : "2026-02-03T14:23:51.690Z"
    },
    "hasDateModified" : {
      "@type" : "dateTime",
      "@value" : "2026-04-01T08:52:30.545Z"
    },
    "hasDateProduced" : {
      "@type" : "gYear",
      "@value" : "2026"
    },
    "hasGenre" : [ {
      "@id" : "http://metadatahub.bijnpo.nl/f0e72f47-115c-42f6-b27d-2b09ca757fe0",
      "@type" : "Genre",
      "broader" : {
        "@id" : "http://metadatahub.bijnpo.nl/93fe4130-ce74-41dd-8abc-174ff7be8bb6",
        "@type" : "Genre",
        "inScheme" : {
          "@id" : "http://metadatahub.bijnpo.nl/GenreScheme"
        },
        "notation" : "3.0.1.7",
        "prefLabel" : "Informatief"
      },
      "inScheme" : {
        "@id" : "http://metadatahub.bijnpo.nl/GenreScheme"
      },
      "notation" : "3.0.1.7.23",
      "prefLabel" : "Informatief-Koken/eten"
    } ],
    "hasIdentifier" : [ {
      "@id" : "http://metadatahub.bijnpo.nl/b4e0202b-883a-4821-a8fc-3a3bdae29a82",
      "@type" : "Identifier",
      "identifierValue" : "BROADCAST",
      "name" : "Original POMS type"
    }, {
      "@id" : "http://metadatahub.bijnpo.nl/41d6e728-4f66-449b-98f2-fdd2023eae3d",
      "@type" : "Identifier",
      "hasObjectType" : {
        "@id" : "http://metadatahub.bijnpo.nl/240895a4-7c12-4224-b5c0-8fe1837904d3",
        "@type" : "Concept",
        "date" : "2007-04-12",
        "definition" : "An identifying number issued by the organisation supplying the material (in this case a complete programme) and recognised by them as such.",
        "inScheme" : {
          "@id" : "urn:ebu:metadata-cs:IdentifierTypeCodeCS"
        },
        "notation" : "1.6",
        "prefLabel" : "Programme Number"
      },
      "identifierValue" : "POW_06003920",
      "name" : "PRID"
    }, {
      "@id" : "http://metadatahub.bijnpo.nl/a63963e0-1fc8-4dd4-98a5-72304748eeb3",
      "@type" : "Identifier",
      "hasObjectType" : {
        "@id" : "http://metadatahub.bijnpo.nl/bacaa8e3-e7cc-48d3-a2fe-fdd92d803a92",
        "@type" : "Concept",
        "date" : "2007-04-12",
        "definition" : "ETSI. Content Reference identifier. A globally unique identifier defined by TV-Anytime.",
        "inScheme" : {
          "@id" : "urn:ebu:metadata-cs:IdentifierTypeCodeCS"
        },
        "notation" : "3.1",
        "prefLabel" : "Crid"
      },
      "identifierValue" : "crid://npo/programmagegevens/2560759193668",
      "name" : "CRID"
    }, {
      "@id" : "http://metadatahub.bijnpo.nl/b539d091-94dc-4105-b518-a5d2b3a51431",
      "@type" : "Identifier",
      "hasObjectType" : "http://metadatahub.bijnpo.nl/bacaa8e3-e7cc-48d3-a2fe-fdd92d803a92",
      "identifierValue" : "crid://npo/programmagegevens/2560399952668",
      "name" : "CRID"
    }, {
      "@id" : "http://metadatahub.bijnpo.nl/b9930b3c-1bf6-47c1-9380-31f598bf1fad",
      "@type" : "Identifier",
      "hasObjectType" : "http://metadatahub.bijnpo.nl/bacaa8e3-e7cc-48d3-a2fe-fdd92d803a92",
      "identifierValue" : "crid://npo/programmagegevens/2562758464668",
      "name" : "CRID"
    } ],
    "hasOriginalLanguage" : {
      "@id" : "http://metadatahub.bijnpo.nl/f2dd127b-f190-4016-a5c2-bcb7a53b7922",
      "@type" : "Language",
      "notation" : "nl",
      "prefLabel" : "Nederlands"
    },
    "hasPublication" : [ {
      "@id" : "http://metadatahub.bijnpo.nl/191e80c5-d990-45f2-aacb-91d8c6c15584",
      "@type" : "PublicationEvent",
      "hasDuration" : {
        "@id" : "http://metadatahub.bijnpo.nl/b3419144-1f92-4605-a2e9-317e2dc6f412",
        "@type" : "TimelinePoint",
        "equivalentTime" : {
          "@type" : "float",
          "@value" : "777000.0"
        }
      },
      "hasPublicationChannel" : {
        "@id" : "http://metadatahub.bijnpo.nl/b69adfea-3e30-4dd9-90b1-bcae480e8236",
        "@type" : "PublicationChannel",
        "hasPublicationPlatform" : {
          "@id" : "http://metadatahub.bijnpo.nl/135769ac-af17-48b1-ad24-297d7369605e"
        },
        "name" : "NPO 2"
      },
      "hasStartDateTime" : {
        "@type" : "dateTime",
        "@value" : "2026-03-25T11:15:00.000Z"
      },
      "playsOut" : {
        "@id" : "http://metadatahub.bijnpo.nl/0bb3fa35-2d70-4509-ba68-da404199ea6b",
        "@type" : "Essence",
        "hasFormat" : "http://metadatahub.bijnpo.nl/4ddc7c30-33d5-40db-816f-53038f012b08"
      },
      "publishes" : "http://metadatahub.bijnpo.nl/fa77fc39-01bf-496f-ba72-cc3dedf8f2a8"
    }, {
      "@id" : "http://metadatahub.bijnpo.nl/3c06e3c2-9042-46e5-bee2-ef690a3f58af",
      "@type" : "PublicationEvent",
      "hasDuration" : {
        "@id" : "http://metadatahub.bijnpo.nl/a8c79e9d-777e-4814-a244-80b52f807ebd",
        "@type" : "TimelinePoint",
        "equivalentTime" : {
          "@type" : "float",
          "@value" : "776000.0"
        }
      },
      "hasPublicationChannel" : "http://metadatahub.bijnpo.nl/b69adfea-3e30-4dd9-90b1-bcae480e8236",
      "hasStartDateTime" : {
        "@type" : "dateTime",
        "@value" : "2026-04-01T14:10:00.000Z"
      },
      "playsOut" : "http://metadatahub.bijnpo.nl/0bb3fa35-2d70-4509-ba68-da404199ea6b",
      "publishes" : "http://metadatahub.bijnpo.nl/fa77fc39-01bf-496f-ba72-cc3dedf8f2a8"
    }, {
      "@id" : "http://metadatahub.bijnpo.nl/6c18b788-e9b9-4d91-ad51-168855188385",
      "@type" : "PublicationEvent",
      "hasDuration" : {
        "@id" : "http://metadatahub.bijnpo.nl/90440555-31ea-40de-8b1b-3db800cfaa2f",
        "@type" : "TimelinePoint",
        "equivalentTime" : {
          "@type" : "float",
          "@value" : "847000.0"
        }
      },
      "hasPublicationChannel" : {
        "@id" : "http://metadatahub.bijnpo.nl/fe62b8a6-1abd-4901-94af-2c47e4adc44d",
        "@type" : "PublicationChannel",
        "hasPublicationPlatform" : {
          "@id" : "http://metadatahub.bijnpo.nl/135769ac-af17-48b1-ad24-297d7369605e"
        },
        "name" : "NPO 1"
      },
      "hasStartDateTime" : {
        "@type" : "dateTime",
        "@value" : "2026-03-25T12:20:00.000Z"
      },
      "playsOut" : "http://metadatahub.bijnpo.nl/0bb3fa35-2d70-4509-ba68-da404199ea6b",
      "publishes" : "http://metadatahub.bijnpo.nl/fa77fc39-01bf-496f-ba72-cc3dedf8f2a8"
    }, {
      "@id" : "http://metadatahub.bijnpo.nl/fc64adb1-e0e7-4af7-9205-1ff9440ea6dd",
      "@type" : "PublicationEvent",
      "hasEndDateTime" : {
        "@type" : "dateTime",
        "@value" : "2100-01-01T00:00:00.000Z"
      },
      "hasPublicationChannel" : {
        "@id" : "http://metadatahub.bijnpo.nl/8aa838a6-a14d-41d9-87cb-92d22d4c38d3",
        "@type" : "PublicationChannel",
        "hasPublicationPlatform" : {
          "@id" : "http://metadatahub.bijnpo.nl/8ba0d9a7-f2dc-4cad-ac81-05f5bb72bbc1"
        },
        "name" : "INTERNETVOD"
      },
      "hasStartDateTime" : {
        "@type" : "dateTime",
        "@value" : "2026-03-25T11:38:32.566Z"
      },
      "playsOut" : "http://metadatahub.bijnpo.nl/0bb3fa35-2d70-4509-ba68-da404199ea6b",
      "publishes" : "http://metadatahub.bijnpo.nl/fa77fc39-01bf-496f-ba72-cc3dedf8f2a8"
    }, {
      "@id" : "http://metadatahub.bijnpo.nl/e755b1e8-c0e9-4a84-a598-8e8735930351",
      "@type" : "PublicationEvent",
      "hasDuration" : {
        "@id" : "http://metadatahub.bijnpo.nl/0b7daea8-5116-4e10-a075-bda683dee02b",
        "@type" : "TimelinePoint",
        "equivalentTime" : {
          "@type" : "float",
          "@value" : "764000.0"
        }
      },
      "hasPublicationChannel" : {
        "@id" : "http://metadatahub.bijnpo.nl/390db5f2-0b43-4e4c-8178-ce33571cdab0",
        "@type" : "PublicationChannel",
        "hasPublicationPlatform" : {
          "@id" : "http://metadatahub.bijnpo.nl/135769ac-af17-48b1-ad24-297d7369605e"
        },
        "name" : "BVN"
      },
      "hasStartDateTime" : {
        "@type" : "dateTime",
        "@value" : "2026-03-25T13:35:00.000Z"
      },
      "playsOut" : "http://metadatahub.bijnpo.nl/0bb3fa35-2d70-4509-ba68-da404199ea6b",
      "publishes" : "http://metadatahub.bijnpo.nl/fa77fc39-01bf-496f-ba72-cc3dedf8f2a8"
    }, {
      "@id" : "http://metadatahub.bijnpo.nl/fd394497-6d87-42e4-8f9d-125682d49c5c",
      "@type" : "PublicationEvent",
      "hasDuration" : {
        "@id" : "http://metadatahub.bijnpo.nl/775427ea-790d-41c7-a995-0d094c817399",
        "@type" : "TimelinePoint",
        "equivalentTime" : {
          "@type" : "float",
          "@value" : "764000.0"
        }
      },
      "hasPublicationChannel" : "http://metadatahub.bijnpo.nl/390db5f2-0b43-4e4c-8178-ce33571cdab0",
      "hasStartDateTime" : {
        "@type" : "dateTime",
        "@value" : "2026-03-26T01:35:00.000Z"
      },
      "playsOut" : "http://metadatahub.bijnpo.nl/0bb3fa35-2d70-4509-ba68-da404199ea6b",
      "publishes" : "http://metadatahub.bijnpo.nl/fa77fc39-01bf-496f-ba72-cc3dedf8f2a8"
    }, {
      "@id" : "http://metadatahub.bijnpo.nl/36bc9461-01ce-4668-a17d-45b65deaa347",
      "@type" : "PublicationEvent",
      "hasEndDateTime" : {
        "@type" : "dateTime",
        "@value" : "2031-03-25T12:35:42.320Z"
      },
      "hasPublicationChannel" : {
        "@id" : "http://metadatahub.bijnpo.nl/102b2a29-7d41-4c36-b6a7-76d7b4a7545c",
        "@type" : "PublicationChannel",
        "hasPublicationPlatform" : {
          "@id" : "http://metadatahub.bijnpo.nl/8ba0d9a7-f2dc-4cad-ac81-05f5bb72bbc1"
        },
        "name" : "PLUSVOD"
      },
      "hasStartDateTime" : {
        "@type" : "dateTime",
        "@value" : "2026-03-25T11:42:24.402Z"
      },
      "playsOut" : "http://metadatahub.bijnpo.nl/0bb3fa35-2d70-4509-ba68-da404199ea6b",
      "publishes" : "http://metadatahub.bijnpo.nl/fa77fc39-01bf-496f-ba72-cc3dedf8f2a8"
    } ],
    "hasPublisher" : [ {
      "@id" : "http://metadatahub.bijnpo.nl/6a0cff4b-851d-4223-9545-68aa1a1a5611",
      "@type" : "Involvement",
      "hasAgent" : {
        "@id" : "http://metadatahub.bijnpo.nl/60df11e9-2164-4370-bae6-dd26f3c3a705",
        "@type" : "Agent",
        "hasIdentifier" : [ "http://metadatahub.bijnpo.nl/1a88c28f-82e1-4134-9cfb-745b69b81047" ],
        "name" : "MAX"
      },
      "hasObjectType" : {
        "@id" : "http://metadatahub.bijnpo.nl/bb054996-02e3-4b19-9550-74d9d99866b9",
        "@type" : "Concept",
        "date" : "2007-04-12",
        "definition" : "A person or organisation that sends out or communicates material, especially by radio or television",
        "inScheme" : {
          "@id" : "urn:ebu:metadata-cs:RoleCodeCS"
        },
        "notation" : "10.9.1",
        "prefLabel" : "Broadcaster"
      }
    } ],
    "hasRating" : [ {
      "@id" : "http://metadatahub.bijnpo.nl/de5dc134-ff0b-4134-bd08-7ee3adc37a2c",
      "@type" : "AudienceRating",
      "description" : "Suitable for all ages",
      "hasObjectType" : {
        "@id" : "http://metadatahub.bijnpo.nl/86e458ed-a4dc-4bcb-a24c-bc192ca836c2",
        "@type" : "Concept",
        "definition" : [ {
          "@language" : "nl",
          "@value" : "Alle leeftijden"
        }, {
          "@language" : "en",
          "@value" : "Suitable for all ages"
        } ],
        "inScheme" : {
          "@id" : "urn:ebu:metadata-cs:ContentAlertSchemeCodeCS"
        },
        "notation" : "37.1.1",
        "prefLabel" : "AL"
      },
      "ratingProvider" : {
        "@id" : "http://metadatahub.bijnpo.nl/38a39f2b-2ae3-4852-8252-b90af8953104",
        "@type" : "Organisation",
        "hasObjectType" : "http://metadatahub.bijnpo.nl/40ad78cf-3079-4a5d-85c1-446da49e258c",
        "label" : "NICAM (Kijkwijzer)",
        "homepage" : "http://www.kijkwijzer.nl/"
      },
      "ratingSystemName" : "NL-NICAM",
      "ratingValue" : "AL"
    } ],
    "hasRelatedPicture" : [ {
      "@id" : "http://metadatahub.bijnpo.nl/41cf74cb-50ac-47d2-bb27-568918234d54",
      "@type" : "Picture",
      "highlighted" : {
        "@type" : "boolean",
        "@value" : "false"
      },
      "imageType" : "STILL",
      "description" : "Sandra maakt toast met tuinbonenspread en een gepocheerd ei met frisse citroenyoghurt. Een echt lentegerecht.",
      "frameHeight" : {
        "@type" : "integer",
        "@value" : "1080"
      },
      "frameWidth" : {
        "@type" : "integer",
        "@value" : "1920"
      },
      "hasCopyright" : {
        "@id" : "http://metadatahub.bijnpo.nl/b9777b5a-5923-4c14-a8fd-e95b97be1563",
        "@type" : "Copyright",
        "hasObjectType" : "http://metadatahub.bijnpo.nl/7772331f-2af1-48c4-a210-8bc36889cf49",
        "hasRightsHolder" : "http://metadatahub.bijnpo.nl/4ddfdf96-689f-49cb-842f-3232f781c0c5"
      },
      "hasDateCreated" : {
        "@type" : "dateTime",
        "@value" : "2026-03-24T06:46:29.930Z"
      },
      "hasDateModified" : {
        "@type" : "dateTime",
        "@value" : "2026-03-24T06:46:29.930Z"
      },
      "hasIdentifier" : [ {
        "@id" : "http://metadatahub.bijnpo.nl/54afe7a3-d9b2-4c70-91d0-8d902648e75b",
        "@type" : "Identifier",
        "identifierValue" : "urn:vpro:image:2234296",
        "name" : "Image URI"
      }, {
        "@id" : "http://metadatahub.bijnpo.nl/28723d4a-7117-49bd-b04f-e8d3adc54870",
        "@type" : "Identifier",
        "identifierValue" : "urn:vpro:media:image:132060577",
        "name" : "Image URN"
      } ],
      "hasPublisher" : [ {
        "@id" : "http://metadatahub.bijnpo.nl/6145f42b-6496-4d05-b8ff-bef1f2699c8d",
        "@type" : "Involvement",
        "hasAgent" : "http://metadatahub.bijnpo.nl/238a44bd-9143-44fb-8933-13db05ba1212",
        "hasObjectType" : "http://metadatahub.bijnpo.nl/bb054996-02e3-4b19-9550-74d9d99866b9"
      } ],
      "pubStatus" : "PUBLISHED",
      "title" : "Kook mee met MAX"
    }, {
      "@id" : "http://metadatahub.bijnpo.nl/5bb53546-35f7-4f80-b3ef-c8c7f7639bda",
      "@type" : "Picture",
      "highlighted" : {
        "@type" : "boolean",
        "@value" : "false"
      },
      "imageType" : "STILL",
      "description" : "Sandra maakt toast met tuinbonenspread en een gepocheerd ei met frisse citroenyoghurt. Een echt lentegerecht.",
      "frameHeight" : {
        "@type" : "integer",
        "@value" : "1080"
      },
      "frameWidth" : {
        "@type" : "integer",
        "@value" : "1920"
      },
      "hasCopyright" : {
        "@id" : "http://metadatahub.bijnpo.nl/7d81cd72-0b33-4aa8-bf87-c19490c037af",
        "@type" : "Copyright",
        "hasObjectType" : "http://metadatahub.bijnpo.nl/7772331f-2af1-48c4-a210-8bc36889cf49",
        "hasRightsHolder" : "http://metadatahub.bijnpo.nl/4ddfdf96-689f-49cb-842f-3232f781c0c5"
      },
      "hasDateCreated" : {
        "@type" : "dateTime",
        "@value" : "2026-03-24T06:46:39.875Z"
      },
      "hasDateModified" : {
        "@type" : "dateTime",
        "@value" : "2026-03-24T06:46:39.875Z"
      },
      "hasIdentifier" : [ {
        "@id" : "http://metadatahub.bijnpo.nl/1cb1ea29-2c56-4962-bc8a-221e51b235c1",
        "@type" : "Identifier",
        "identifierValue" : "urn:vpro:media:image:132060579",
        "name" : "Image URN"
      }, {
        "@id" : "http://metadatahub.bijnpo.nl/3bc4acf4-db34-4fbc-92dd-8f17aa8b6a10",
        "@type" : "Identifier",
        "identifierValue" : "urn:vpro:image:2234298",
        "name" : "Image URI"
      } ],
      "pubStatus" : "PUBLISHED",
      "title" : "Kook mee met MAX"
    }, {
      "@id" : "http://metadatahub.bijnpo.nl/73668576-45f3-4ca1-8048-664cc571a865",
      "@type" : "Picture",
      "highlighted" : {
        "@type" : "boolean",
        "@value" : "false"
      },
      "imageType" : "STILL",
      "description" : "Sandra maakt toast met tuinbonenspread en een gepocheerd ei met frisse citroenyoghurt. Een echt lentegerecht.",
      "frameHeight" : {
        "@type" : "integer",
        "@value" : "1080"
      },
      "frameWidth" : {
        "@type" : "integer",
        "@value" : "1920"
      },
      "hasCopyright" : {
        "@id" : "http://metadatahub.bijnpo.nl/7620fb67-a80f-44bf-b1b5-328de60f1fc1",
        "@type" : "Copyright",
        "hasObjectType" : "http://metadatahub.bijnpo.nl/7772331f-2af1-48c4-a210-8bc36889cf49",
        "hasRightsHolder" : "http://metadatahub.bijnpo.nl/4ddfdf96-689f-49cb-842f-3232f781c0c5"
      },
      "hasDateCreated" : {
        "@type" : "dateTime",
        "@value" : "2026-03-24T06:46:35.480Z"
      },
      "hasDateModified" : {
        "@type" : "dateTime",
        "@value" : "2026-03-24T06:46:35.480Z"
      },
      "hasIdentifier" : [ {
        "@id" : "http://metadatahub.bijnpo.nl/b3826e9d-a39d-47b0-894b-17980304b7b9",
        "@type" : "Identifier",
        "identifierValue" : "urn:vpro:image:2234297",
        "name" : "Image URI"
      }, {
        "@id" : "http://metadatahub.bijnpo.nl/f4d9e88b-038c-4d42-a293-81bfa75bcba2",
        "@type" : "Identifier",
        "identifierValue" : "urn:vpro:media:image:132060578",
        "name" : "Image URN"
      } ],
      "pubStatus" : "PUBLISHED",
      "title" : "Kook mee met MAX"
    } ],
    "hasRights" : [ {
      "@id" : "http://metadatahub.bijnpo.nl/fc711ebd-3832-45b8-b2a9-31abb601429b",
      "@type" : "Rights",
      "hasRightsTargetChannel" : {
        "@id" : "http://metadatahub.bijnpo.nl/8aa838a6-a14d-41d9-87cb-92d22d4c38d3"
      },
      "hasRightsTerritoryIncludes" : {
        "@id" : "http://metadatahub.bijnpo.nl/97746efe-30be-4271-a730-a0719cd2e67d",
        "@type" : "Concept",
        "definition" : "Expliciet geen geo-restricties.",
        "inScheme" : {
          "@id" : "urn:npo:metadata-cs:TerritoryCodeCS"
        },
        "prefLabel" : "Wereld"
      }
    }, {
      "@id" : "http://metadatahub.bijnpo.nl/439c4b75-09a7-4703-b6ff-896bb6555f69",
      "@type" : "Rights",
      "hasRightsTargetChannel" : {
        "@id" : "http://metadatahub.bijnpo.nl/102b2a29-7d41-4c36-b6a7-76d7b4a7545c"
      },
      "hasRightsTerritoryIncludes" : "http://metadatahub.bijnpo.nl/97746efe-30be-4271-a730-a0719cd2e67d"
    } ],
    "isEpisodeOfSeason" : {
      "@id" : "http://metadatahub.bijnpo.nl/f1e2d489-9201-48e8-bad7-3e61731bd577",
      "@type" : "Season",
      "contentDescription" : "Wat eten we vanavond? Topkoks Sandra Ysbrandy en Mounir Toub geven antwoord op die ene moeilijke vraag. Ze bereiden makkelijke en verrassende gerechten.",
      "hasDateCreated" : {
        "@type" : "dateTime",
        "@value" : "2025-11-25T13:40:13.384Z"
      },
      "hasDateModified" : {
        "@type" : "dateTime",
        "@value" : "2026-05-06T12:56:56.303Z"
      },
      "hasGenre" : [ "http://metadatahub.bijnpo.nl/f0e72f47-115c-42f6-b27d-2b09ca757fe0" ],
      "hasIdentifier" : [ {
        "@id" : "http://metadatahub.bijnpo.nl/60d06975-e1e5-44f7-864d-a910140d3302",
        "@type" : "Identifier",
        "identifierValue" : "SEASON",
        "name" : "Original POMS type"
      }, {
        "@id" : "http://metadatahub.bijnpo.nl/0bf6578b-bfad-41c4-9f87-32254704f68f",
        "@type" : "Identifier",
        "hasObjectType" : "http://metadatahub.bijnpo.nl/240895a4-7c12-4224-b5c0-8fe1837904d3",
        "identifierValue" : "POW_06003873",
        "name" : "PRID"
      } ],
      "hasPublisher" : [ {
        "@id" : "http://metadatahub.bijnpo.nl/d1502bdf-c284-4331-b717-26ba37a0cae2",
        "@type" : "Involvement",
        "hasAgent" : "http://metadatahub.bijnpo.nl/60df11e9-2164-4370-bae6-dd26f3c3a705",
        "hasObjectType" : "http://metadatahub.bijnpo.nl/bb054996-02e3-4b19-9550-74d9d99866b9"
      } ],
      "isSeasonOf" : {
        "@id" : "http://metadatahub.bijnpo.nl/68029acb-4c62-4b82-ae93-bf5d1c319a18",
        "@type" : "Series",
        "hasAlternativeContentDescription" : [ "http://metadatahub.bijnpo.nl/49db7435-bf5f-4199-b22d-7cd80dfdb462" ],
        "contentDescription" : "Wat eten we vanavond? Topkoks Sandra Ysbrandy en Mounir Toub geven antwoord op die ene moeilijke vraag. Ze bereiden makkelijke en verrassende gerechten.",
        "hasDateCreated" : {
          "@type" : "dateTime",
          "@value" : "2017-07-17T17:37:30.863Z"
        },
        "hasDateModified" : {
          "@type" : "dateTime",
          "@value" : "2026-05-06T11:33:14.316Z"
        },
        "hasIdentifier" : [ "http://metadatahub.bijnpo.nl/2418f52d-f307-483a-ba41-cdc267c9aae9", "http://metadatahub.bijnpo.nl/d4df6955-dfc0-43ee-b053-9197cd64f3ae" ],
        "hasPublisher" : [ "http://metadatahub.bijnpo.nl/6584a1d2-3b19-49a0-b529-a32fabc9157d" ],
        "hasRelatedPicture" : [ "http://metadatahub.bijnpo.nl/52cbf755-a780-4b5a-bf38-28e7d06cdae1" ],
        "isMemberOf" : [ "http://metadatahub.bijnpo.nl/e0a53051-216f-4432-bf4c-1700d3009688", "http://metadatahub.bijnpo.nl/9e72bd41-a595-4ac5-99af-fc77ffadca46" ],
        "orderedFlag" : {
          "@type" : "boolean",
          "@value" : "true"
        },
        "pubStatus" : "PUBLISHED",
        "title" : "Kook mee met MAX"
      },
      "orderedFlag" : {
        "@type" : "boolean",
        "@value" : "true"
      },
      "pubStatus" : "PUBLISHED",
      "seasonNumber" : {
        "@type" : "integer",
        "@value" : "8"
      },
      "title" : "Kook mee met MAX"
    },
    "isInstantiatedBy" : {
      "@id" : "http://metadatahub.bijnpo.nl/f98679f0-7ce4-45f8-8e78-4c20ef42d7af",
      "@type" : "MediaResource",
      "hasRelatedEssence" : "http://metadatahub.bijnpo.nl/0bb3fa35-2d70-4509-ba68-da404199ea6b"
    },
    "pubStatus" : "PUBLISHED",
    "represents" : [ {
      "@id" : "http://metadatahub.bijnpo.nl/7ca44731-d2f4-4a2f-8e3c-06404ddb2d6c",
      "@type" : "Asset",
      "hasAccessConditions" : [ {
        "@id" : "http://metadatahub.bijnpo.nl/c473921f-ca66-4d47-8128-bf7ae2bc024e",
        "@type" : "AccessConditions",
        "ec:hasGeoBlockingWhitelist" : "NLALL"
      }, {
        "@id" : "http://metadatahub.bijnpo.nl/337696fb-b5c0-481e-83b3-13665f4dd037",
        "@type" : "AccessConditions",
        "ec:hasGeoBlockingWhitelist" : "PLUSVOD:WR"
      } ]
    }, {
      "@id" : "http://metadatahub.bijnpo.nl/61875370-732f-4162-ba49-2c10e334a7ea",
      "@type" : "Asset",
      "hasAccessConditions" : {
        "@id" : "http://metadatahub.bijnpo.nl/150c7dc0-0b7e-4f5d-a5ff-b703a01e6097",
        "@type" : "AccessConditions",
        "ec:hasGeoBlockingWhitelist" : "WR"
      }
    } ],
    "title" : "Toast met tuinbonenspread, ei en citroenyoghurt"
  },
  "error" : ""
}