<?xml version="1.0" encoding="UTF-8" standalone="yes"?>
<program xmlns="urn:vpro:media:2009" xmlns:shared="urn:vpro:shared:2009" type="BROADCAST" avType="VIDEO" embeddable="true" mid="VPWON_1368155" sortDate="2026-03-31T22:00:00+02:00" workflow="PUBLISHED" creationDate="2026-02-11T15:40:59.019+01:00" lastModified="2026-04-02T14:53:23.342+02:00" publishDate="2026-04-02T14:54:30.724+02:00" urn="urn:vpro:media:program:131868774">
    <crid>crid://npo/programmagegevens/2562758343668</crid>
    <crid>crid://npo/programmagegevens/2562757758668</crid>
    <crid>crid://npo/programmagegevens/2562757718668</crid>
    <crid>crid://npo/programmagegevens/2562757935668</crid>
    <crid>crid://npo/programmagegevens/2574329758668</crid>
    <crid>crid://npo/programmagegevens/2574329826668</crid>
    <broadcaster id="NOS">NOS</broadcaster>
    <broadcaster id="NTR">NTR</broadcaster>
    <region regionId="WR" platform="INTERNETVOD"/>
    <region regionId="EU" platform="PLUSVOD"/>
    <title owner="MIS" type="MAIN">Nieuwsuur</title>
    <description owner="MIS" type="MAIN">Kidane H. staat in Nederland terecht voor een omvangrijke mensensmokkelzaak. Verslaggever Mark Schrader volgt de zaak en is in de studio. * Een derde van de Nederlandse gemeenten maakt gebruik van een noodknop. Dat blijkt uit onderzoek van Nieuwsuur. Met zo'n noodknop staat iemand meteen in contact met de meldkamer van de politie. * Het Israëlische parlement, de Knesset, is akkoord gegaan met een zeer omstreden wetsvoorstel om de doodstraf in te voeren voor moord met terroristisch motief. We praten erover met Peter Malcontent, universiteit hoofddocent internationale betrekkingen aan de Universiteit Utrecht.</description>
    <description owner="MIS" type="SHORT">Beruchte mensensmokkelaar voor de rechter * Personeel heeft vaker een noodknop * Parlement Israël stemt in met omstreden wet voor doodstraf</description>
    <genre id="3.0.1.7.21">
        <term>Informatief</term>
        <term>Nieuws/actualiteiten</term>
    </genre>
    <country code="NL">Nederland</country>
    <language code="nl">Nederlands</language>
    <isDubbed>false</isDubbed>
    <releaseYear>2026</releaseYear>
    <duration>P0DT0H36M10.000S</duration>
    <credits>
        <person externalId="whatson:1565324770517" role="PRESENTER">
            <givenName>Jeroen</givenName>
            <familyName>Wollaars</familyName>
        </person>
    </credits>
    <descendantOf urnRef="urn:vpro:media:group:111089395" midRef="POMS_S_NPO_15374575" type="PLAYLIST"/>
    <descendantOf urnRef="urn:vpro:media:group:131486785" midRef="VPWON_1368067" type="SEASON"/>
    <descendantOf urnRef="urn:vpro:media:group:70883859" midRef="VPWON_1246712" type="SERIES"/>
    <descendantOf urnRef="urn:vpro:media:group:74848353" midRef="POMS_S_NPO_3760702" type="COLLECTION"/>
    <descendantOf urnRef="urn:vpro:media:group:74908339" midRef="POMS_S_NPO_3767333" type="COLLECTION"/>
    <descendantOf urnRef="urn:vpro:media:group:75112033" midRef="POMS_S_NPO_3792628" type="COLLECTION"/>
    <descendantOf urnRef="urn:vpro:media:group:95895388" midRef="POMS_S_NPO_9798311" type="COLLECTION"/>
    <descendantOf urnRef="urn:vpro:media:group:97022679" midRef="POMS_S_NPO_10444886" type="PLAYLIST"/>
    <descendantOf urnRef="urn:vpro:media:group:97133697" midRef="POMS_S_NPO_10505903" type="PLAYLIST"/>
    <prediction state="ANNOUNCED" publishStart="2000-01-01T01:00:00+01:00" publishStop="2101-01-01T00:59:00+01:00">INTERNETVOD</prediction>
    <prediction state="ANNOUNCED" publishStart="2026-03-31T22:36:07+02:00" publishStop="2027-03-31T22:36:07+02:00">PLUSVOD</prediction>
    <locations/>
    <images/>
    <scheduleEvents>
        <scheduleEvent channel="NED2" midRef="VPWON_1368155" urnRef="urn:vpro:media:program:131868774">
            <textSubtitles>Teletekst ondertitels</textSubtitles>
            <guideDay>2026-03-31+02:00</guideDay>
            <start>2026-03-31T22:00:00+02:00</start>
            <duration>P0DT0H35M29.000S</duration>
            <poProgID>VPWON_1368155</poProgID>
        </scheduleEvent>
        <scheduleEvent channel="BVNT" midRef="VPWON_1368155" urnRef="urn:vpro:media:program:131868774">
            <repeat isRerun="true"/>
            <textSubtitles>Teletekst ondertitels</textSubtitles>
            <guideDay>2026-03-31+02:00</guideDay>
            <start>2026-03-31T22:20:00+02:00</start>
            <duration>P0DT0H35M32.000S</duration>
            <poProgID>VPWON_1368155</poProgID>
        </scheduleEvent>
        <scheduleEvent channel="NED2" midRef="VPWON_1368155" urnRef="urn:vpro:media:program:131868774">
            <repeat isRerun="true"/>
            <textSubtitles>Teletekst ondertitels</textSubtitles>
            <guideDay>2026-03-31+02:00</guideDay>
            <start>2026-03-31T23:55:00+02:00</start>
            <duration>P0DT0H36M20.000S</duration>
            <poProgID>VPWON_1368155</poProgID>
        </scheduleEvent>
        <scheduleEvent channel="NED2" midRef="VPWON_1368155" urnRef="urn:vpro:media:program:131868774">
            <repeat isRerun="true"/>
            <textSubtitles>Teletekst ondertitels</textSubtitles>
            <guideDay>2026-03-31+02:00</guideDay>
            <start>2026-04-01T01:15:00+02:00</start>
            <duration>P0DT0H36M11.000S</duration>
            <poProgID>VPWON_1368155</poProgID>
        </scheduleEvent>
        <scheduleEvent channel="NED2" midRef="VPWON_1368155" urnRef="urn:vpro:media:program:131868774">
            <repeat isRerun="true"/>
            <textSubtitles>Teletekst ondertitels</textSubtitles>
            <guideDay>2026-03-31+02:00</guideDay>
            <start>2026-04-01T02:35:00+02:00</start>
            <duration>P0DT0H36M22.000S</duration>
            <poProgID>VPWON_1368155</poProgID>
        </scheduleEvent>
        <scheduleEvent channel="NED2" midRef="VPWON_1368155" urnRef="urn:vpro:media:program:131868774">
            <repeat isRerun="true"/>
            <textSubtitles>Teletekst ondertitels</textSubtitles>
            <guideDay>2026-03-31+02:00</guideDay>
            <start>2026-04-01T03:50:00+02:00</start>
            <duration>P0DT0H36M11.000S</duration>
            <poProgID>VPWON_1368155</poProgID>
        </scheduleEvent>
        <scheduleEvent channel="NED2" midRef="VPWON_1368155" urnRef="urn:vpro:media:program:131868774">
            <repeat isRerun="true"/>
            <textSubtitles>Teletekst ondertitels</textSubtitles>
            <guideDay>2026-04-01+02:00</guideDay>
            <start>2026-04-01T09:50:00+02:00</start>
            <duration>P0DT0H36M19.000S</duration>
            <poProgID>VPWON_1368155</poProgID>
        </scheduleEvent>
        <scheduleEvent channel="BVNT" midRef="VPWON_1368155" urnRef="urn:vpro:media:program:131868774">
            <repeat isRerun="true"/>
            <textSubtitles>Teletekst ondertitels</textSubtitles>
            <guideDay>2026-03-31+02:00</guideDay>
            <start>2026-04-01T10:20:00+02:00</start>
            <duration>P0DT0H35M32.000S</duration>
            <poProgID>VPWON_1368155</poProgID>
        </scheduleEvent>
    </scheduleEvents>
    <episodeOf added="2026-02-11T15:40:59.881+01:00" highlighted="false" midRef="VPWON_1368067" index="88" type="SEASON" urnRef="urn:vpro:media:group:131486785">
        <memberOf midRef="VPWON_1246712" type="SERIES" index="18">
            <memberOf midRef="POMS_S_NPO_15374575" type="PLAYLIST" index="12"/>
            <memberOf midRef="POMS_S_NPO_10505903" type="PLAYLIST" index="13">
                <memberOf midRef="POMS_S_NPO_9798311" type="COLLECTION"/>
            </memberOf>
            <memberOf midRef="POMS_S_NPO_10444886" type="PLAYLIST" index="15">
                <memberOf midRef="POMS_S_NPO_9798311" type="COLLECTION"/>
            </memberOf>
            <memberOf midRef="POMS_S_NPO_3767333" type="COLLECTION">
                <memberOf midRef="POMS_S_NPO_3760702" type="COLLECTION">
                    <memberOf midRef="POMS_S_NPO_3792628" type="COLLECTION" index="5"/>
                </memberOf>
            </memberOf>
        </memberOf>
    </episodeOf>
    <segments/>
</program>
